LICENSE
setup.py
piletools/__init__.py
piletools/piletools.py
piletools.egg-info/PKG-INFO
piletools.egg-info/SOURCES.txt
piletools.egg-info/dependency_links.txt
piletools.egg-info/entry_points.txt
piletools.egg-info/requires.txt
piletools.egg-info/top_level.txt