Metadata-Version: 2.1
Name: piletools
Version: 0.21.2
Summary: Mpileup analysis toolkit.
Home-page: https://git.lumc.nl/j.f.j.laros/piletools
Author: LUMC, Jeroen F.J. Laros
Author-email: j.f.j.laros@lumc.nl
License: MIT License
Keywords: bioinformatics
Platform: any
Classifier: Development Status :: 3 - Alpha
Classifier: Intended Audience :: Science/Research
Classifier: Intended Audience :: Developers
Classifier: Operating System :: OS Independent
Classifier: Programming Language :: Python
Classifier: Topic :: Scientific/Engineering
License-File: LICENSE
